kaxanuk/data_curator/__init__.py
kaxanuk/data_curator/config_handlers/__init__.py
kaxanuk/data_curator/config_handlers/configurator_interface.py
kaxanuk/data_curator/config_handlers/excel_configurator.py
kaxanuk/data_curator/data_blocks/__init__.py
kaxanuk/data_curator/data_blocks/base_data_block.py
kaxanuk/data_curator/data_blocks/dividends/__init__.py
kaxanuk/data_curator/data_blocks/fundamentals/__init__.py
kaxanuk/data_curator/data_blocks/market_daily/__init__.py
kaxanuk/data_curator/data_blocks/splits/__init__.py
kaxanuk/data_curator/data_curator.py
kaxanuk/data_curator/data_providers/__init__.py
kaxanuk/data_curator/data_providers/data_provider_interface.py
kaxanuk/data_curator/data_providers/financial_modeling_prep.py
kaxanuk/data_curator/data_providers/not_found.py
kaxanuk/data_curator/entities/__init__.py
kaxanuk/data_curator/entities/base_data_entity.py
kaxanuk/data_curator/entities/configuration.py
kaxanuk/data_curator/entities/dividend_data.py
kaxanuk/data_curator/entities/dividend_data_row.py
kaxanuk/data_curator/entities/fundamental_data.py
kaxanuk/data_curator/entities/fundamental_data_row.py
kaxanuk/data_curator/entities/fundamental_data_row_balance_sheet.py
kaxanuk/data_curator/entities/fundamental_data_row_cash_flow.py
kaxanuk/data_curator/entities/fundamental_data_row_income_statement.py
kaxanuk/data_curator/entities/main_identifier.py
kaxanuk/data_curator/entities/market_data.py
kaxanuk/data_curator/entities/market_data_daily_row.py
kaxanuk/data_curator/entities/market_instrument_identifier.py
kaxanuk/data_curator/entities/split_data.py
kaxanuk/data_curator/entities/split_data_row.py
kaxanuk/data_curator/exceptions/__init__.py
kaxanuk/data_curator/features/__init__.py
kaxanuk/data_curator/features/calculations.py
kaxanuk/data_curator/features/helpers.py
kaxanuk/data_curator/modules/__init__.py
kaxanuk/data_curator/modules/data_column.py
kaxanuk/data_curator/modules/debugger.py
kaxanuk/data_curator/modules/dotenv_loader.py
kaxanuk_data_curator-0.45.0.dist-info/METADATA
kaxanuk_data_curator-0.45.0.dist-info/WHEEL
kaxanuk_data_curator-0.45.0.dist-info/entry_points.txt
kaxanuk_data_curator-0.45.0.dist-info/licenses/LICENSE
kaxanuk_data_curator-0.45.0.dist-info/RECORD
