Metadata-Version: 2.1
Name: kaxanuk.data_curator
Version: 0.45.0
Summary: Tool for retrieving and combining financial and related data for informing security investments
Author-Email: KaxaNuk <info@kaxanuk.mx>, Rinku Kazeno <rinku.kazeno@kaxanuk.mx>, Ruben Flores <ruben.flores@kaxanuk.mx>, Arturo Aguilar <arturo.aguilar@kaxanuk.mx>
License: MIT License
Classifier: Development Status :: 4 - Beta
Classifier: License :: OSI Approved :: MIT License
Classifier: Programming Language :: Python :: 3
Project-URL: Homepage, https://kaxanuk.mx
Project-URL: Documentation, https://kaxanuk-data-curator.readthedocs.io/en/stable/api_reference/index.html
Project-URL: Repository, https://github.com/KaxaNuk/Data-Curator
Project-URL: Issues, https://github.com/KaxaNuk/Data-Curator/issues
Project-URL: Changelog, https://github.com/KaxaNuk/Data-Curator/blob/main/CHANGELOG.md
Requires-Python: <3.14,>=3.12
Requires-Dist: click>=8.1.7
Requires-Dist: networkx>=3.5
Requires-Dist: openpyxl>=3.1.5
Requires-Dist: packaging>=24.2
Requires-Dist: pandas>=2.2.3
Requires-Dist: pyarrow>=18.0
Requires-Dist: python-dotenv>=1.0.1
